tictoc/__init__.py
tictoc/tictoc.py
tictoc_borisgorelik-0.0.3.dist-info/LICENSE
tictoc_borisgorelik-0.0.3.dist-info/METADATA
tictoc_borisgorelik-0.0.3.dist-info/WHEEL
tictoc_borisgorelik-0.0.3.dist-info/top_level.txt
tictoc_borisgorelik-0.0.3.dist-info/RECORD
