Metadata-Version: 2.1
Name: tictoc-borisgorelik
Version: 0.0.3
Summary: A simple way to measure execution time
Home-page: https://github.com/bgbg/tictoc
Author: Boris Gorelik
Author-email: boris@gorelik.net
License: UNKNOWN
Platform: UNKNOWN
Classifier: Programming Language :: Python :: 3
Classifier: License :: OSI Approved :: MIT License
Classifier: Operating System :: OS Independent
Requires-Python: >=3.6
